periplus_proxy/__init__.py
periplus_proxy/controller.py
periplus_proxy/models.py
periplus_proxy-0.1.0a1.dist-info/LICENSE
periplus_proxy-0.1.0a1.dist-info/METADATA
periplus_proxy-0.1.0a1.dist-info/WHEEL
periplus_proxy-0.1.0a1.dist-info/top_level.txt
periplus_proxy-0.1.0a1.dist-info/RECORD
